{
  "complex_cigar.sam": "timeout",
  "htsjdk_coordinate_sorted.sam": "timeout",
  "jazzer_large_02475821.sam": "timeout",
  "jazzer_large_13dda956.sam": "rc=0 throw The required LN tag in @SQ is missing. [38]",
  "jazzer_large_1b280906.sam": "rc=0 throw The required SN tag in @SQ is missing. [38]",
  "jazzer_large_1d2b3402.sam": "timeout",
  "jazzer_large_1d58d514.sam": "rc=0 throw Illegal SAM header tag starting with:Z [38]",
  "jazzer_large_2491b4c7.sam": "timeout",
  "jazzer_large_4e6d29d9.sam": "timeout",
  "jazzer_large_70bda767.sam": "timeout",
  "jazzer_large_7b2873f3.sam": "oserror:13",
  "jazzer_large_7bb59360.sam": "oserror:13",
  "jazzer_medium_029a2980.sam": "oserror:13",
  "jazzer_medium_08b3daaa.sam": "oserror:13",
  "jazzer_medium_0b96ac39.sam": "oserror:13",
  "jazzer_medium_13ef2794.sam": "oserror:13",
  "jazzer_medium_1ced3d59.sam": "oserror:13",
  "jazzer_medium_210fd1b8.sam": "oserror:13",
  "jazzer_medium_28dcae2a.sam": "oserror:13",
  "jazzer_medium_29943d0c.sam": "oserror:13",
  "jazzer_medium_2a7eb109.sam": "oserror:13",
  "jazzer_medium_3137e5dc.sam": "oserror:13",
  "jazzer_small_00027f3f.sam": "oserror:13",
  "jazzer_small_001ba165.sam": "oserror:13",
  "jazzer_small_013bf3e8.sam": "oserror:13",
  "jazzer_small_02c388c4.sam": "oserror:13",
  "jazzer_small_05ce597f.sam": "oserror:13",
  "jazzer_small_0725e4b2.sam": "oserror:13",
  "jazzer_small_0a009423.sam": "oserror:13",
  "jazzer_small_0bb2a0ab.sam": "oserror:13",
  "jazzer_small_0cc1388b.sam": "oserror:13",
  "jazzer_small_0e138ae1.sam": "oserror:13",
  "literals_biopython_b_arrays.sam": "oserror:13",
  "literals_biopython_md_cigar.sam": "oserror:13",
  "literals_htsjdk_cigar_ops.sam": "oserror:13",
  "literals_htsjdk_flags.sam": "oserror:13",
  "literals_htsjdk_optional_types.sam": "oserror:13",
  "literals_seqan3_h_hex.sam": "oserror:13",
  "literals_seqan3_pg_hd.sam": "oserror:13",
  "minimal_tags.sam": "oserror:13",
  "rawfuzz_0084e34c21124473.sam": "oserror:13",
  "rawfuzz_01cc78e4caebd529.sam": "oserror:13",
  "rawfuzz_0208cd6b2a89f5c7.sam": "oserror:13",
  "rawfuzz_02a879547329d9ab.sam": "oserror:13",
  "rawfuzz_02ead9d9c1f97367.sam": "oserror:13",
  "rawfuzz_03209420a467520d.sam": "oserror:13",
  "rawfuzz_03645d1dc9fa7732.sam": "oserror:13",
  "rawfuzz_03ff14238e397d42.sam": "oserror:13",
  "rawfuzz_042749c39f06981c.sam": "oserror:13",
  "rawfuzz_0432511031d89d99.sam": "oserror:13",
  "rawfuzz_0488e5f23323073a.sam": "oserror:13",
  "rawfuzz_04f8466009a4ea94.sam": "oserror:13",
  "rawfuzz_05344552803ec89d.sam": "oserror:13",
  "rawfuzz_054bafc303fda2ad.sam": "oserror:13",
  "rawfuzz_05701be65d36bbf4.sam": "oserror:13",
  "rawfuzz_057a68ea663d4fe4.sam": "oserror:13",
  "rawfuzz_05b0224b928ce183.sam": "oserror:13",
  "rawfuzz_06940a742cabf5ba.sam": "oserror:13",
  "rawfuzz_0697bbff3cf8b788.sam": "oserror:13",
  "rawfuzz_069f2e0bbfa63976.sam": "oserror:13",
  "rawfuzz_06a0b4cba86aec59.sam": "oserror:13",
  "rawfuzz_06c47f27f27de8b7.sam": "oserror:13",
  "rawfuzz_06d0986b39cadac9.sam": "oserror:13",
  "rawfuzz_06df834265f4616f.sam": "oserror:13",
  "rawfuzz_06e555d0052f3882.sam": "oserror:13",
  "rawfuzz_0708da32afad9066.sam": "oserror:13",
  "rawfuzz_07ab0a044eee43ee.sam": "oserror:13",
  "rawfuzz_07ee61ce06698778.sam": "oserror:13",
  "rawfuzz_07f4787b5a71de8d.sam": "oserror:13",
  "rawfuzz_0941f7ac6c192f53.sam": "oserror:13",
  "rawfuzz_0a28f4a0fb0358fd.sam": "oserror:13",
  "rawfuzz_0a333a4b62c3d0b2.sam": "oserror:13",
  "rawfuzz_0a5c0defbdc2b361.sam": "oserror:13",
  "rawfuzz_0ad31ee46b24e1f7.sam": "oserror:13",
  "rawfuzz_0b5157f09b7cc66c.sam": "oserror:13",
  "rawfuzz_0cb1251e37d2f83f.sam": "oserror:13",
  "rawfuzz_0cda4113ce0d15e1.sam": "oserror:13",
  "rawfuzz_0cef6b59353349e6.sam": "oserror:13",
  "rawfuzz_0cfbbbfd0d47f82c.sam": "oserror:13",
  "rawfuzz_0da436aed5d86093.sam": "oserror:13",
  "rawfuzz_0e09dd759d77f1f7.sam": "oserror:13",
  "rawfuzz_0e442155774c2142.sam": "oserror:13",
  "rawfuzz_0f33146df6ac35c7.sam": "oserror:13",
  "rawfuzz_0f955f986a30300b.sam": "oserror:13",
  "rawfuzz_0fa642ffe6f3a34d.sam": "oserror:13",
  "rawfuzz_100d4b432e7eda78.sam": "oserror:13",
  "rawfuzz_10874b8616f1b132.sam": "oserror:13",
  "rawfuzz_1087b4cdaceef578.sam": "oserror:13",
  "rawfuzz_10a757c4ec4ffce1.sam": "oserror:13",
  "rawfuzz_110fd6a70c84721e.sam": "oserror:13",
  "rawfuzz_1173a0f1e4388c89.sam": "oserror:13",
  "rawfuzz_11cceb11b7a63901.sam": "oserror:13",
  "rawfuzz_120d210e9ed56943.sam": "oserror:13",
  "rawfuzz_13b2111895b7ea14.sam": "oserror:13",
  "rawfuzz_13d87e7b399b8f77.sam": "oserror:13",
  "rawfuzz_14ad3dc9d9fa784b.sam": "oserror:13",
  "rawfuzz_14e869ef13fc4f95.sam": "oserror:13",
  "rawfuzz_170559bf8f266ac7.sam": "oserror:13",
  "rawfuzz_17651f3bec309f6c.sam": "oserror:13",
  "rawfuzz_17ed69402deffe25.sam": "oserror:13",
  "rawfuzz_18055a00edc0a524.sam": "oserror:13",
  "rawfuzz_18395671fcbc0605.sam": "oserror:13",
  "rawfuzz_18e0761a9d805eee.sam": "oserror:13",
  "rawfuzz_19eb6502c8e3d641.sam": "oserror:13",
  "rawfuzz_1a03e47fb79629d4.sam": "oserror:13",
  "rawfuzz_1a324007eb85d09b.sam": "oserror:13",
  "rawfuzz_1a44435e3ab6ce1f.sam": "oserror:13",
  "rawfuzz_1b8cc2e0197bd60c.sam": "oserror:13",
  "rawfuzz_1bd0835e5968ef4f.sam": "oserror:13",
  "rawfuzz_1bf00fa0ad99fdcb.sam": "oserror:13",
  "rawfuzz_1c21b727109f78f3.sam": "oserror:13",
  "rawfuzz_1d416f27d4c5ebd1.sam": "oserror:13",
  "rawfuzz_1d4f6b62d12b3e20.sam": "oserror:13",
  "rawfuzz_1d6bb4f282762722.sam": "oserror:13",
  "rawfuzz_1dbbefc795f8cb0b.sam": "oserror:13",
  "rawfuzz_1e8bab32875585e8.sam": "oserror:13",
  "rawfuzz_1ea3a4280a0303de.sam": "oserror:13",
  "rawfuzz_1ee69c510c8fdbd6.sam": "oserror:13",
  "rawfuzz_202f36313620b33a.sam": "oserror:13",
  "rawfuzz_20e821d2665a1d65.sam": "oserror:13"
}